templo/__init__.py
templo/lex.py
templo/lexer.py
templo/parser.py
templo/parser_error.py
templo/parsetab.py
templo/run.py
templo/tests.py
templo/yacc.py
templo-0.1.0.dist-info/LICENSE.txt
templo-0.1.0.dist-info/METADATA
templo-0.1.0.dist-info/WHEEL
templo-0.1.0.dist-info/top_level.txt
templo-0.1.0.dist-info/RECORD
