Metadata-Version: 2.1
Name: templo
Version: 0.1.0
Summary: Generic template language.
Home-page: UNKNOWN
License: UNKNOWN
Platform: UNKNOWN
Classifier: Programming Language :: Python :: 3.10
Classifier: License :: OSI Approved :: GNU General Public License v3 or later (GPLv3+)
Classifier: Operating System :: OS Independent
License-File: LICENSE.txt
Requires-Dist: ply (~=3.11)
Provides-Extra: dev
Requires-Dist: ply (~=3.11) ; extra == 'dev'
Requires-Dist: twine ; extra == 'dev'
